bugbountysa-1.0.0.dist-info/licenses/LICENSE
core/__init__.py
core/analysis.py
core/config.py
core/domains.py
core/programs.py
core/scope.py
core/utils.py
bugbountysa-1.0.0.dist-info/METADATA
bugbountysa-1.0.0.dist-info/WHEEL
bugbountysa-1.0.0.dist-info/entry_points.txt
bugbountysa-1.0.0.dist-info/top_level.txt
bugbountysa-1.0.0.dist-info/RECORD
