Metadata-Version: 2.4
Name: bugbountysa
Version: 1.0.0
Summary: A tool for managing Bug Bounty SA programs in Saudi Arabia
Author-email: ShulkwiSEC <shulkwisec@gmail.com>
License-Expression: MIT
Project-URL: Homepage, https://github.com/ShulkwiSEC/bugbountysa
Project-URL: Bug Reports, https://github.com/ShulkwiSEC/bugbountysa/issues
Project-URL: Source, https://github.com/ShulkwiSEC/bugbountysa
Keywords: bug bounty,security,pentesting,saudi arabia,automation
Classifier: Development Status :: 5 - Production/Stable
Classifier: Intended Audience :: Developers
Classifier: Operating System :: OS Independent
Classifier: Programming Language :: Python :: 3
Classifier: Programming Language :: Python :: 3.8
Classifier: Programming Language :: Python :: 3.9
Classifier: Programming Language :: Python :: 3.10
Classifier: Programming Language :: Python :: 3.11
Classifier: Programming Language :: Python :: 3.12
Classifier: Topic :: Internet :: WWW/HTTP :: Dynamic Content
Classifier: Topic :: Software Development :: Libraries :: Python Modules
Requires-Python: >=3.8
License-File: LICENSE
Requires-Dist: requests>=2.28.0
Requires-Dist: colorama>=0.4.6
Requires-Dist: tabulate>=0.9.0
Requires-Dist: rich>=13.0.0
Requires-Dist: python-dateutil>=2.8.2
Requires-Dist: tqdm>=4.65.0
Requires-Dist: urllib3>=2.0.0
Requires-Dist: python-dotenv>=1.0.0
Dynamic: license-file
